doc_track-0.1.4.dist-info/licenses/LICENSE
doctrack/__init__.py
doctrack/checker.py
doctrack/cli.py
doctrack/config.py
doctrack/output.py
doctrack/commands/__init__.py
doctrack/commands/check.py
tests/__init__.py
tests/checker/__init__.py
tests/checker/test_checker_python.py
doc_track-0.1.4.dist-info/METADATA
doc_track-0.1.4.dist-info/WHEEL
doc_track-0.1.4.dist-info/entry_points.txt
doc_track-0.1.4.dist-info/top_level.txt
doc_track-0.1.4.dist-info/RECORD
