Metadata-Version: 2.4
Name: doc-track
Version: 0.1.4
Summary: Command that helps keeping track of piece of code marked as 'documented'
Home-page: https://github.com/Seals-co/doc-track/
Author: Ratinax
Project-URL: Source, https://github.com/Seals-co/doc-track/
Project-URL: Tracker, https://github.com/Seals-co/doc-track/issues/
Requires-Python: >=3.7
License-File: LICENSE
Requires-Dist: pyyaml==6.0.2
Dynamic: author
Dynamic: description
Dynamic: description-content-type
Dynamic: home-page
Dynamic: license-file
Dynamic: project-url
Dynamic: requires-dist
Dynamic: requires-python
Dynamic: summary
